[
    {
        "value": "萌",
        "parts": [
            {
                "value": "明",
                "parts": [
                    {
                        "value": "日",
                        "parts": []
                    },
                    {
                        "value": "月",
                        "parts": []
                    }
                ]
            },
            {
                "value": "くさかんむり",
                "parts": []
            }
        ]
    },
    {
        "value": "明",
        "parts": [
            {
                "value": "日",
                "parts": []
            },
            {
                "value": "月",
                "parts": []
            }
        ]
    },
    {
        "value": "盟",
        "parts": [
            {
                "value": "明",
                "parts": [
                    {
                        "value": "日",
                        "parts": []
                    },
                    {
                        "value": "月",
                        "parts": []
                    }
                ]
            },
            {
                "value": "皿",
                "parts": []
            }
        ]
    },
    {
        "value": "林",
        "parts": [
            {
                "value": "木",
                "parts": []
            },
            {
                "value": "木",
                "parts": []
            }
        ]
    }
]